{
	"parent": "unbreakable:recipes/root",
	"criteria": {
		"has_netherite_shovel": {
			"trigger": "minecraft:inventory_changed",
			"conditions": {
				"items": [{ "items": "minecraft:netherite_shovel" }]
			}
		},
		"has_the_recipe": {
			"trigger": "minecraft:recipe_unlocked",
			"conditions": {
				"recipe": "unbreakable:unbreakable_netherite_shovel_smithing"
			}
		}
	},
	"requirements": [["has_netherite_shovel", "has_the_recipe"]],
	"rewards": {
		"recipes": ["unbreakable:unbreakable_netherite_shovel_smithing"]
	}
}
